{"cameraMode":{"drawMode":0,"name":"Shaded","section":"Shading Mode"},"sceneLighting":true,"audioPlay":false,"sceneViewState":{"m_AlwaysRefresh":false,"showFog":true,"showSkybox":true,"showFlares":true,"showImageEffects":true,"showParticleSystems":true,"showVisualEffectGraphs":true,"m_FxEnabled":true},"in2DMode":false,"pivot":{"x":415.3616638183594,"y":-4.798623085021973,"z":57.0291862487793},"rotation":{"x":-0.21442869305610658,"y":-0.30820176005363467,"z":0.07150041311979294,"w":-0.9241068959236145},"size":15.523171424865723,"orthographic":false}