{"cameraMode":{"drawMode":0,"name":"Shaded","section":"Shading Mode"},"sceneLighting":true,"audioPlay":false,"sceneViewState":{"m_AlwaysRefresh":false,"showFog":true,"showSkybox":true,"showFlares":true,"showImageEffects":true,"showParticleSystems":true,"showVisualEffectGraphs":true,"m_FxEnabled":true},"in2DMode":false,"pivot":{"x":404.9932556152344,"y":-5.548811435699463,"z":54.74071502685547},"rotation":{"x":-0.01721128262579441,"y":0.9813820719718933,"z":-0.15919025242328645,"w":-0.10610421001911164},"size":10.871040344238282,"orthographic":false}